qualityscaler/QualityScaler.py
qualityscaler/__init__.py
qualityscaler/cli.py
quality_scaler-2.12.9.dist-info/LICENSE
quality_scaler-2.12.9.dist-info/LICENSE.txt
quality_scaler-2.12.9.dist-info/METADATA
quality_scaler-2.12.9.dist-info/WHEEL
quality_scaler-2.12.9.dist-info/entry_points.txt
quality_scaler-2.12.9.dist-info/top_level.txt
quality_scaler-2.12.9.dist-info/RECORD
